cryptocom/__init__.py
cryptocom/exchange/__init__.py
cryptocom/exchange/api.py
cryptocom/exchange/helpers.py
cryptocom/exchange/instruments.py
cryptocom/exchange/market.py
cryptocom/exchange/pairs.py
cryptocom/exchange/private.py
cryptocom/exchange/structs.py
cryptocom_exchange-0.15.0.dist-info/LICENSE
cryptocom_exchange-0.15.0.dist-info/METADATA
cryptocom_exchange-0.15.0.dist-info/WHEEL
cryptocom_exchange-0.15.0.dist-info/RECORD
