Metadata-Version: 2.1
Name: cryptocom-exchange
Version: 0.15.0
Summary: Python 3.9+ async library for crypto.com/exchange API using httpx and websockets
License: MIT
Author: Morty Space
Author-email: morty.space@gmail.com
Requires-Python: >=3.9,<4.0
Classifier: License :: OSI Approved :: MIT License
Classifier: Operating System :: OS Independent
Classifier: Programming Language :: Python :: 3
Classifier: Programming Language :: Python :: 3.9
Classifier: Programming Language :: Python :: 3.10
Classifier: Programming Language :: Python :: 3.11
Classifier: Programming Language :: Python :: 3.12
Classifier: Programming Language :: Python :: Implementation :: CPython
Classifier: Topic :: Software Development :: Libraries :: Python Modules
Requires-Dist: aiolimiter (>=1.0.0,<2.0.0)
Requires-Dist: async-timeout (>=4.0.2,<5.0.0)
Requires-Dist: cached-property (>=1.5.2,<2.0.0)
Requires-Dist: httpx (>=0.27.0,<0.28.0)
Requires-Dist: pyyaml (>=6.0.2,<7.0.0)
Requires-Dist: websockets (>=10.3,<11.0)
